{"format-version":2,"table-uuid":"d3e3beb5-00c9-4254-a323-05ac9ae34a52","location":"/tmp/iceberg_v2_aggregate_warehouse/retail/retail_sales","last-sequence-number":1,"last-updated-ms":1774691655032,"last-column-id":11,"current-schema-id":0,"schemas":[{"type":"struct","schema-id":0,"fields":[{"id":1,"name":"sale_id","required":true,"type":"int"},{"id":2,"name":"store_name","required":true,"type":"string"},{"id":3,"name":"region","required":true,"type":"string"},{"id":4,"name":"category","required":true,"type":"string"},{"id":5,"name":"product_name","required":true,"type":"string"},{"id":6,"name":"quantity","required":true,"type":"int"},{"id":7,"name":"unit_price","required":true,"type":"double"},{"id":8,"name":"discount_pct","required":true,"type":"double"},{"id":9,"name":"sale_date","required":true,"type":"string"},{"id":10,"name":"salesperson","required":true,"type":"string"},{"id":11,"name":"is_return","required":true,"type":"int"}]}],"default-spec-id":0,"partition-specs":[{"spec-id":0,"fields":[]}],"last-partition-id":999,"default-sort-order-id":0,"sort-orders":[{"order-id":0,"fields":[]}],"properties":{"owner":"chess","write.update.mode":"merge-on-read","write.delete.mode":"merge-on-read","write.parquet.compression-codec":"zstd"},"current-snapshot-id":8556301251813537930,"refs":{"main":{"snapshot-id":8556301251813537930,"type":"branch"}},"snapshots":[{"sequence-number":1,"snapshot-id":8556301251813537930,"timestamp-ms":1774691655032,"summary":{"operation":"append","spark.app.id":"local-1774691646082","added-data-files":"1","added-records":"120","added-files-size":"5362","changed-partition-count":"1","total-records":"120","total-files-size":"5362","total-data-files":"1","total-delete-files":"0","total-position-deletes":"0","total-equality-deletes":"0","engine-version":"4.0.0","app-id":"local-1774691646082","engine-name":"spark","iceberg-version":"Apache Iceberg 1.10.1 (commit ccb8bc435062171e64bc8b7e5f56e6aed9c5b934)"},"manifest-list":"/tmp/iceberg_v2_aggregate_warehouse/retail/retail_sales/metadata/snap-8556301251813537930-1-c195cfa1-31b0-4826-9c51-d588ab32c168.avro","schema-id":0}],"statistics":[],"partition-statistics":[],"snapshot-log":[{"timestamp-ms":1774691655032,"snapshot-id":8556301251813537930}],"metadata-log":[{"timestamp-ms":1774691651542,"metadata-file":"/tmp/iceberg_v2_aggregate_warehouse/retail/retail_sales/metadata/v1.metadata.json"}]}